MANIFEST.in
UNLICENSE
setup.py
urlstring/__init__.py
urlstring/compat.py
urlstring/netloc.py
urlstring/path.py
urlstring/ports.py
urlstring/query_string.py
urlstring/six.py
urlstring/urlobject.py
urlstring.egg-info/PKG-INFO
urlstring.egg-info/SOURCES.txt
urlstring.egg-info/dependency_links.txt
urlstring.egg-info/top_level.txt