Metadata-Version: 1.0
Name: urlstring
Version: 2.4.0
Summary: A fork of Zachary Voase's "URLObject" utility class for manipulating URLs.
Home-page: http://github.com/fish2000/urlobject
Author: Alexander Bohn
Author-email: fish2000@gmail.com
License: UNKNOWN
Platform: UNKNOWN
